{
  "id": "exp402",
  "personalInfo": {
    "fullName": "PD Dr. Michael Koch",
    "title": "Senior AI Researcher",
    "email": "michael.koch@rwth-aachen.de",
    "phone": "+49 166 33193926",
    "image": "/experts/michael-koch.jpg",
    "languages": [
      "Spanisch"
    ]
  },
  "institution": {
    "name": "RWTH Aachen",
    "department": "Institut für Künstliche Intelligenz",
    "position": "Researcher",
    "location": "Aachen"
  },
  "expertise": {
    "primary": [
      "Machine Learning",
      "Quantum AI",
      "Deep Learning"
    ],
    "secondary": [
      "Big Data Analytics",
      "AutoML"
    ],
    "industries": [
      "Education",
      "Research",
      "Energy"
    ]
  },
  "currentRole": {
    "title": "Senior AI Researcher",
    "organization": "RWTH Aachen",
    "focus": "Forschung in Deep Learning",
    "status": "active"
  }
}